satellite_py/__init__.py
satellite_py/__init__.pyi
satellite_py-0.1.9.dist-info/METADATA
satellite_py-0.1.9.dist-info/WHEEL
satellite_py-0.1.9.dist-info/top_level.txt
satellite_py-0.1.9.dist-info/RECORD
