Metadata-Version: 2.4
Name: satellite_py
Version: 0.1.9
Summary: utils for project
Requires-Python: >=3.13.2
Requires-Dist: pydantic>=2.11.4
